dict_tape/__init__.py
dict_tape/exceptions.py
dict_tape/traversal.py
dict_tape-1.3.0.dist-info/METADATA
dict_tape-1.3.0.dist-info/WHEEL
dict_tape-1.3.0.dist-info/licenses/LICENSE
dict_tape-1.3.0.dist-info/RECORD
